expose/__init__.py
expose/main.py
expose/requirements.txt
expose/configuration/nginx-non-ssl.conf
expose/configuration/nginx-ssl.conf
expose/configuration/options-ssl-nginx.conf
expose/configuration/server.conf
expose/models/auxiliary.py
expose/models/cert.py
expose/models/config.py
expose/models/exceptions.py
expose/models/image_factory.py
expose/models/logger.py
expose/models/route_53.py
expose/models/server.py
expose_localhost-0.8.dist-info/LICENSE
expose_localhost-0.8.dist-info/METADATA
expose_localhost-0.8.dist-info/WHEEL
expose_localhost-0.8.dist-info/top_level.txt
expose_localhost-0.8.dist-info/RECORD
