Metadata-Version: 2.1
Name: expose-localhost
Version: 0.8
Summary: Reverse proxy that creates a secure tunnel from public endpoint to locally running web service
Author-email: Vignesh Rao <svignesh1793@gmail.com>
License: MIT License
Project-URL: Homepage, https://github.com/thevickypedia/expose
Project-URL: Docs, https://thevickypedia.github.io/expose/
Project-URL: Source, https://github.com/thevickypedia/expose
Project-URL: Bug Tracker, https://github.com/thevickypedia/expose/issues
Project-URL: Release Notes, https://github.com/thevickypedia/expose/blob/main/release_notes.rst
Keywords: route53,certificate,ec2,ngrok-alternative,tunnel
Classifier: Development Status :: 5 - Production/Stable
Classifier: Intended Audience :: Information Technology
Classifier: Operating System :: OS Independent
Classifier: License :: OSI Approved :: MIT License
Classifier: Programming Language :: Python :: 3.9
Classifier: Programming Language :: Python :: 3.8
Classifier: Programming Language :: Python :: 3.9
Classifier: Programming Language :: Python :: 3.10
Classifier: Programming Language :: Python :: 3.11
Classifier: Topic :: System :: Networking :: Firewalls
Requires-Python: >=3
License-File: LICENSE
Requires-Dist: boto3
Requires-Dist: botocore
Requires-Dist: paramiko ==3.3.1
Requires-Dist: pyOpenSSL >=23.2.0
Requires-Dist: inflect >=7.0.0
Requires-Dist: pydantic[email] ==2.3.0
Requires-Dist: pydantic-settings ==2.0.3
Provides-Extra: dev
Requires-Dist: pre-commit ; extra == 'dev'
